LICENSE
MANIFEST.in
README.rst
setup.py
demo/__init__.py
demo/settings.py
demo/urls.py
demo/wsgi.py
demo/todos/__init__.py
demo/todos/admin.py
demo/todos/apps.py
demo/todos/models.py
demo/todos/tests.py
demo/todos/views.py
demo/todos/migrations/0001_initial.py
demo/todos/migrations/0002_auto_20180316_0031.py
demo/todos/migrations/__init__.py
django_simple_viewset.egg-info/PKG-INFO
django_simple_viewset.egg-info/SOURCES.txt
django_simple_viewset.egg-info/dependency_links.txt
django_simple_viewset.egg-info/not-zip-safe
django_simple_viewset.egg-info/top_level.txt
simple_viewset/__init__.py
simple_viewset/views.py
simple_viewset/templates/base.html
simple_viewset/templates/simple_viewset/confirm_delete.html
simple_viewset/templates/simple_viewset/detail.html
simple_viewset/templates/simple_viewset/form.html
simple_viewset/templates/simple_viewset/list.html
simple_viewset/templates/simple_viewset/table.html
simple_viewset/templatetags/simple_viewset_tags.py