Metadata-Version: 1.1
Name: django-simple-viewset
Version: 0.1.10
Summary: Simple viewset for models CRUD operations
Home-page: https://gitlab.com/elcone/django-simple-viewset.git
Author: Alejandro Sánchez
Author-email: elcone@gmail.com
License: MIT
Keywords: django,simple,viewset,crud
Platform: UNKNOWN
Classifier: Development Status :: 3 - Alpha
Classifier: Framework :: Django
Classifier: Framework :: Django :: 1.8
Classifier: Framework :: Django :: 1.9
Classifier: Framework :: Django :: 1.10
Classifier: Intended Audience :: Developers
Classifier: License :: OSI Approved :: BSD License
Classifier: Natural Language :: English
Classifier: Programming Language :: Python :: 2
Classifier: Programming Language :: Python :: 2.7
Classifier: Programming Language :: Python :: 3
Classifier: Programming Language :: Python :: 3.3
Classifier: Programming Language :: Python :: 3.4
Classifier: Programming Language :: Python :: 3.5
